odoo/addons/project_stage_extra_info/README.rst
odoo/addons/project_stage_extra_info/__init__.py
odoo/addons/project_stage_extra_info/__manifest__.py
odoo/addons/project_stage_extra_info/i18n/ca.po
odoo/addons/project_stage_extra_info/i18n/it.po
odoo/addons/project_stage_extra_info/i18n/project_stage_extra_info.pot
odoo/addons/project_stage_extra_info/models/__init__.py
odoo/addons/project_stage_extra_info/models/project_project_stage.py
odoo/addons/project_stage_extra_info/readme/CONTRIBUTORS.md
odoo/addons/project_stage_extra_info/readme/DESCRIPTION.md
odoo/addons/project_stage_extra_info/readme/USAGE.md
odoo/addons/project_stage_extra_info/static/description/icon.png
odoo/addons/project_stage_extra_info/static/description/index.html
odoo/addons/project_stage_extra_info/tests/__init__.py
odoo/addons/project_stage_extra_info/tests/test_project_stage_extra_info.py
odoo/addons/project_stage_extra_info/views/project_stage_view.xml
odoo/addons/project_stage_extra_info/views/project_view.xml
odoo_addon_project_stage_extra_info-18.0.1.0.0.2.dist-info/METADATA
odoo_addon_project_stage_extra_info-18.0.1.0.0.2.dist-info/WHEEL
odoo_addon_project_stage_extra_info-18.0.1.0.0.2.dist-info/top_level.txt
odoo_addon_project_stage_extra_info-18.0.1.0.0.2.dist-info/RECORD
